jnb/__init__.py
jnb/__main__.py
jnb/filegen.py
jnb/nbmeta.py
jnb/parsedata.py
jnb-1.0.0.dist-info/METADATA
jnb-1.0.0.dist-info/WHEEL
jnb-1.0.0.dist-info/RECORD
